<DOMSymbolItem xmlns:xsi="http://www.w3.org/2001/XMLSchema-instance" xmlns="http://ns.adobe.com/xfl/2008/" name="Symbol 8Game" itemID="6a222f35-00000222" lastModified="1780625205">
  <timeline>
    <DOMTimeline name="Symbol 8Game" layerDepthEnabled="true">
      <layers>
        <DOMLayer name="Layer_1" color="#00FFFF" current="true" isSelected="true">
          <frames>
            <DOMFrame index="0" keyMode="9728">
              <elements>
                <DOMBitmapInstance selected="true" libraryItemName="Bitmap 13Game">
                  <transformationPoint>
                    <Point x="99" y="61.75"/>
                  </transformationPoint>
                </DOMBitmapInstance>
              </elements>
            </DOMFrame>
          </frames>
        </DOMLayer>
      </layers>
    </DOMTimeline>
  </timeline>
</DOMSymbolItem>